testbenchs/exp_calc/tesbench.sv
`timescale 1ns/1ps;

module testbench;

parameter   EXP_WID = 8,
            E_WID   = (EXP_WID - 1);


logic [E_WID:0]     a_e, b_e;
logic [EXP_WID:0]   exp_final;
logic               underflow, overflow;
logic               rst;
logic               clk = 0;

/*
O objetivo do bloco é realizar a soma entre os expoentes de A e B
e subtrair o bias ao final.
*/

always #5 clk = !clk;

task reset;
    begin
        rst = 1;
        #5;
        rst = 0;
        #10;
        rst = 1;
        #10;
    end
endtask


fpu_exp_calc dut(.*);


/* -------------------------------------------------------------------------- */
/* SCOREBOARD                                                                  */
/* -------------------------------------------------------------------------- */

int pass = 0;
int fail = 0;

logic [EXP_WID:0] exp_expected;

logic underflow_expected;
logic overflow_expected;

localparam BIAS = 8'b10000001;


/* -------------------------------------------------------------------------- */
/* FORMATAÇÃO DOS LOGS                                                         */
/* -------------------------------------------------------------------------- */

task div;
    begin
        $display("+------+------++---------+---------++---------+---------++--------+");
    end
endtask


task header;
    begin

        div();

        $display(
            "|  Ae  |  Be  || Exp DUT | Exp REF || OV DUT  | UF DUT  || STATUS |"
        );

        div();

    end
endtask


task footer;
    begin

        div();

        $display(
            "| RESULTADO FINAL                                                 |"
        );

        div();

        $display(
            "| PASS  = %-05d                                                   |",
            pass
        );

        $display(
            "| FAIL  = %-05d                                                   |",
            fail
        );

        $display(
            "| TOTAL = %-05d                                                   |",
            pass + fail
        );

        div();

        if(fail == 0)
            $display(
                "| STATUS FINAL: PASS                                              |"
            );
        else
            $display(
                "| STATUS FINAL: FAIL                                              |"
            );

        div();

    end
endtask


task pass_tk;
begin
                    $display(
                    "| %08b | %08b || %09b | %09b ||   %01b/%01b   |   %01b/%01b   ||  PASS  |",
                        a_e,
                        b_e,
                        exp_expected,
                        exp_final,
                        overflow_expected,
                        overflow,
                        underflow_expected,
                        underflow
                    );
end
endtask


task fail_tk;
begin
                    $display(
                    "| %08b | %08b || %09b | %09b ||   %01b/%01b   |   %01b/%01b   ||  FAIL  |",
                        a_e,
                        b_e,
                        exp_expected,
                        exp_final,
                        overflow_expected,
                        overflow,
                        underflow_expected,
                        underflow
                    );
end
endtask

/* -------------------------------------------------------------------------- */
/* SCOREBOARD                                                                  */
/* -------------------------------------------------------------------------- */


/*
//1º condição:
((exp_final == (a_e + b_e + BIAS)) && (exp_final =< 254) && (overflow == 1'b0) && (underflow == 1'b0));

//2º condição:
((exp_final == (a_e + b_e + BIAS)) && (exp_final > 254) && (overflow == 1'b1) && (underflow == 1'b0));

//3º condição:
((exp_final == (a_e + b_e + BIAS)) && (exp_final < 1) && (overflow == 1'b0) && (underflow == 1'b1));

10000010 <= exp_final <= 11111111

*/


task check_op;
        begin
            exp_expected = a_e + b_e + BIAS;
            assert (((exp_expected == (a_e + b_e + BIAS)) && 
                     (exp_final <= 254) && 
                     (exp_final == exp_expected) && 
                     (overflow == 1'b0) && 
                     (underflow == 1'b0)))
                begin
                    div();
                    overflow_expected  = 1'b0;
                    underflow_expected = 1'b0;
                    pass++;
                    pass_tk();
                end
            else
            assert (((exp_expected == (a_e + b_e + BIAS)) && 
                     (exp_final > 254) && 
                     (exp_final == exp_expected) && 
                     (overflow == 1'b1) && 
                     (underflow == 1'b0)))
                begin
                    div();
                    overflow_expected  = 1'b1;
                    underflow_expected = 1'b0;
                    pass++;
                    pass_tk();
                end
            else
            assert (((exp_expected == (a_e + b_e + BIAS)) && 
                     (8'b10000010 <= exp_final) && (exp_final <= 8'b11111111) && 
                     (exp_final == exp_expected) && 
                     (overflow == 1'b0) && 
                     (underflow == 1'b1)))
                begin
                    div();
                    overflow_expected  = 1'b0;
                    underflow_expected = 1'b1;
                    pass++;
                    pass_tk();
                end
            else
                begin
                    div();
                    //verflow_expected  = 1'b0;
                    //underflow_expected = 1'b0;
                    fail++;
                    fail_tk();
                end
        end
endtask

/*
task check_op;

    begin

        exp_expected = a_e + b_e - 127;


        if(exp_final > 254)
            begin

                overflow_expected  = 1'b1;
                underflow_expected = 1'b0;

            end

        else if(exp_final < 1)
            begin

                overflow_expected  = 1'b0;
                underflow_expected = 1'b1;

            end

        else
            begin

                overflow_expected  = 1'b0;
                underflow_expected = 1'b0;

            end


        if(
            (exp_final == exp_expected) &&
            (overflow  == overflow_expected) &&
            (underflow == underflow_expected)
        )
            begin

                pass++;

                $display(
                    "| %08b | %08b || %09b | %09b ||   %01b/%01b   |   %01b/%01b   ||  PASS  |",
                    a_e,
                    b_e,
                    exp_final,
                    exp_expected,
                    overflow_expected,
                    overflow,
                    underflow_expected,
                    underflow
                );

            end

        else
            begin

                fail++;

                $display(
                    "| %08b | %08b || %09b | %09b ||   %01b/%01b   |   %01b/%01b   ||  FAIL  |",
                    a_e,
                    b_e,
                    exp_expected,
                    exp_final,
                    overflow_expected,
                    overflow,
                    underflow_expected,
                    underflow
                );

            end

    end

endtask

*/

/* -------------------------------------------------------------------------- */
/* ESTÍMULOS                                                                   */
/* -------------------------------------------------------------------------- */

task mult_teste;

    integer i;
    integer j;

    begin

        for(i = 1; i < (2**(E_WID+1)); i = i + 1)
            begin

                a_e = i;

                for(j = 1; j < (2**(E_WID+1)); j = j + 1)
                    begin

                        b_e = j;

                        @(posedge clk);
                        #1;

                        check_op();

                    end

            end

    end

endtask


/* -------------------------------------------------------------------------- */
/* SIMULAÇÃO                                                                   */
/* -------------------------------------------------------------------------- */

initial
    begin
        reset();
        header();

        #10;

        mult_teste();

        #10;

        footer();

        $finish;

    end


initial
    begin

        $dumpfile("dump.vcd");

        $dumpvars(0, dut);

    end

endmodule

build/exp_calc/dump.vcd
$date
	Fri Sep  4 15:46:09 2026
$end
$version
	Icarus Verilog
$end
$timescale
	1ps
$end
$scope module testbench $end
$scope module dut $end
$var wire 8 ! a_e [7:0] $end
$var wire 8 " b_e [7:0] $end
$var wire 1 # clk $end
$var wire 1 $ rst $end
$var wire 9 % exp_final [8:0] $end
$var parameter 8 & BIAS $end
$var parameter 32 ' EXP_WID $end
$var parameter 33 ( E_WID $end
$var reg 1 ) overflow $end
$var reg 1 * underflow $end
$upscope $end
$upscope $end
$enddefinitions $end
$comment Show the parameter values. $end
$dumpall
b111 (
b1000 '
b10000001 &
$end
#0
$dumpvars
x*
x)
bx %
1$
0#
bx "
bx !
$end
#5000
0*
0)
0$
1#
#10000
0#
#15000
1#
1$
#20000
0#
#25000
1#
#30000
0#
#35000
1*
1#
b10000011 %
b1 "
b1 !
#36000
b10000100 %
b10 "
#40000
0#
#45000
1#
#46000
b10000101 %
b11 "
#50000
0#
#55000
1#
#56000
b10000110 %
b100 "
#60000
0#
#65000
1#
#66000
b10000111 %
b101 "
#70000
0#
#75000
1#
#76000
b10001000 %
b110 "
#80000
0#
#85000
1#
#86000
b10001001 %
b111 "
#90000
0#
#95000
1#
#96000
b10001010 %
b1000 "
#100000
0#
#105000
1#
#106000
b10001011 %
b1001 "
#110000
0#
#115000
1#
#116000
b10001100 %
b1010 "
#120000
0#
#125000
1#
#126000
b10001101 %
b1011 "
#130000
0#
#135000
1#
#136000
b10001110 %
b1100 "
#140000
0#
#145000
1#
#146000
b10001111 %
b1101 "
#150000
0#
#155000
1#
#156000
b10010000 %
b1110 "
#160000
0#
#165000
1#
#166000
b10010001 %
b1111 "
#170000
0#
#175000
1#
#176000
b10010010 %
b10000 "
#180000
0#
#185000
1#
#186000
b10010011 %
b10001 "
#190000
0#
#195000
1#
#196000
b10010100 %
b10010 "
#200000
0#
#205000
1#
#206000
b10010101 %
b10011 "
#210000
0#
#215000
1#
#216000
b10010110 %
b10100 "
#220000
0#
#225000
1#
#226000
b10010111 %
b10101 "
#230000
0#
#235000
1#
#236000
b10011000 %
b10110 "
#240000
0#
#245000
1#
#246000
b10011001 %
b10111 "
#250000
0#
#255000
1#
#256000
b10011010 %
b11000 "
#260000
0#
#265000
1#
#266000
b10011011 %
b11001 "
#270000
0#
#275000
1#
#276000
b10011100 %
b11010 "
#280000
0#
#285000
1#
#286000
b10011101 %
b11011 "
#290000
0#
#295000
1#
#296000
b10011110 %
b11100 "
#300000
0#
#305000
1#
#306000
b10011111 %
b11101 "
#310000
0#
#315000
1#
#316000
b10100000 %
b11110 "
#320000
0#
#325000
1#
#326000
b10100001 %
b11111 "
#330000
0#
#335000
1#
#336000
b10100010 %
b100000 "
#340000
0#
#345000
1#
#346000
b10100011 %
b100001 "
#350000
0#
#355000
1#
#356000
b10100100 %
b100010 "
#360000
0#
#365000
1#
#366000
b10100101 %
b100011 "
#370000
0#
#375000
1#
#376000
b10100110 %
b100100 "
#380000
0#
#385000
1#
#386000
b10100111 %
b100101 "
#390000
0#
#395000
1#
#396000
b10101000 %
b100110 "
#400000
0#
#405000
1#
#406000
b10101001 %
b100111 "
#410000
0#
#415000
1#
#416000
b10101010 %
b101000 "
#420000
0#
#425000
1#
#426000
b10101011 %
b101001 "
#430000
0#
#435000
1#
#436000
b10101100 %
b101010 "
#440000
0#
#445000
1#
#446000
b10101101 %
b101011 "
#450000
0#
#455000
1#
#456000
b10101110 %
b101100 "
#460000
0#
#465000
1#
#466000
b10101111 %
b101101 "
#470000
0#
#475000
1#
#476000
b10110000 %
b101110 "
#480000
0#
#485000
1#
#486000
b10110001 %
b101111 "
#490000
0#
#495000
1#
#496000
b10110010 %
b110000 "
#500000
0#
#505000
1#
#506000
b10110011 %
b110001 "
#510000
0#
#515000
1#
#516000
b10110100 %
b110010 "
#520000
0#
#525000
1#
#526000
b10110101 %
b110011 "
#530000
0#
#535000
1#
#536000
b10110110 %
b110100 "
#540000
0#
#545000
1#
#546000
b10110111 %
b110101 "
#550000
0#
#555000
1#
#556000
b10111000 %
b110110 "
#560000
0#
#565000
1#
#566000
b10111001 %
b110111 "
#570000
0#
#575000
1#
#576000
b10111010 %
b111000 "
#580000
0#
#585000
1#
#586000
b10111011 %
b111001 "
#590000
0#
#595000
1#
#596000
b10111100 %
b111010 "
#600000
0#
#605000
1#
#606000
b10111101 %
b111011 "
#610000
0#
#615000
1#
#616000
b10111110 %
b111100 "
#620000
0#
#625000
1#
#626000
b10111111 %
b111101 "
#630000
0#
#635000
1#
#636000
b11000000 %
b111110 "
#640000
0#
#645000
1#
#646000
b11000001 %
b111111 "
#650000
0#
#655000
1#
#656000
b11000010 %
b1000000 "
#660000
0#
#665000
1#
#666000
b11000011 %
b1000001 "
#670000
0#
#675000
1#
#676000
b11000100 %
b1000010 "
#680000
0#
#685000
1#
#686000
b11000101 %
b1000011 "
#690000
0#
#695000
1#
#696000
b11000110 %
b1000100 "
#700000
0#
#705000
1#
#706000
b11000111 %
b1000101 "
#710000
0#
#715000
1#
#716000
b11001000 %
b1000110 "
#720000
0#
#725000
1#
#726000
b11001001 %
b1000111 "
#730000
0#
#735000
1#
#736000
b11001010 %
b1001000 "
#740000
0#
#745000
1#
#746000
b11001011 %
b1001001 "
#750000
0#
#755000
1#
#756000
b11001100 %
b1001010 "
#760000
0#
#765000
1#
#766000
b11001101 %
b1001011 "
#770000
0#
#775000
1#
#776000
b11001110 %
b1001100 "
#780000
0#
#785000
1#
#786000
b11001111 %
b1001101 "
#790000
0#
#795000
1#
#796000
b11010000 %
b1001110 "
#800000
0#
#805000
1#
#806000
b11010001 %
b1001111 "
#810000
0#
#815000
1#
#816000
b11010010 %
b1010000 "
#820000
0#
#825000
1#
#826000
b11010011 %
b1010001 "
#830000
0#
#835000
1#
#836000
b11010100 %
b1010010 "
#840000
0#
#845000
1#
#846000
b11010101 %
b1010011 "
#850000
0#
#855000
1#
#856000
b11010110 %
b1010100 "
#860000
0#
#865000
1#
#866000
b11010111 %
b1010101 "
#870000
0#
#875000
1#
#876000
b11011000 %
b1010110 "
#880000
0#
#885000
1#
#886000
b11011001 %
b1010111 "
#890000
0#
#895000
1#
#896000
b11011010 %
b1011000 "
#900000
0#
#905000
1#
#906000
b11011011 %
b1011001 "
#910000
0#
#915000
1#
#916000
b11011100 %
b1011010 "
#920000
0#
#925000
1#
#926000
b11011101 %
b1011011 "
#930000
0#
#935000
1#
#936000
b11011110 %
b1011100 "
#940000
0#
#945000
1#
#946000
b11011111 %
b1011101 "
#950000
0#
#955000
1#
#956000
b11100000 %
b1011110 "
#960000
0#
#965000
1#
#966000
b11100001 %
b1011111 "
#970000
0#
#975000
1#
#976000
b11100010 %
b1100000 "
#980000
0#
#985000
1#
#986000
b11100011 %
b1100001 "
#990000
0#
#995000
1#
#996000
b11100100 %
b1100010 "
#1000000
0#
#1005000
1#
#1006000
b11100101 %
b1100011 "
#1010000
0#
#1015000
1#
#1016000
b11100110 %
b1100100 "
#1020000
0#
#1025000
1#
#1026000
b11100111 %
b1100101 "
#1030000
0#
#1035000
1#
#1036000
b11101000 %
b1100110 "
#1040000
0#
#1045000
1#
#1046000
b11101001 %
b1100111 "
#1050000
0#
#1055000
1#
#1056000
b11101010 %
b1101000 "
#1060000
0#
#1065000
1#
#1066000
b11101011 %
b1101001 "
#1070000
0#
#1075000
1#
#1076000
b11101100 %
b1101010 "
#1080000
0#
#1085000
1#
#1086000
b11101101 %
b1101011 "
#1090000
0#
#1095000
1#
#1096000
b11101110 %
b1101100 "
#1100000
0#
#1105000
1#
#1106000
b11101111 %
b1101101 "
#1110000
0#
#1115000
1#
#1116000
b11110000 %
b1101110 "
#1120000
0#
#1125000
1#
#1126000
b11110001 %
b1101111 "
#1130000
0#
#1135000
1#
#1136000
b11110010 %
b1110000 "
#1140000
0#
#1145000
1#
#1146000
b11110011 %
b1110001 "
#1150000
0#
#1155000
1#
#1156000
b11110100 %
b1110010 "
#1160000
0#
#1165000
1#
#1166000
b11110101 %
b1110011 "
#1170000
0#
#1175000
1#
#1176000
b11110110 %
b1110100 "
#1180000
0#
#1185000
1#
#1186000
b11110111 %
b1110101 "
#1190000
0#
#1195000
1#
#1196000
b11111000 %
b1110110 "
#1200000
0#
#1205000
1#
#1206000
b11111001 %
b1110111 "
#1210000
0#
#1215000
1#
#1216000
b11111010 %
b1111000 "
#1220000
0#
#1225000
1#
#1226000
b11111011 %
b1111001 "
#1230000
0#
#1235000
1#
#1236000
b11111100 %
b1111010 "
#1240000
0#
#1245000
1#
#1246000
b11111101 %
b1111011 "
#1250000
0#
#1255000
1#
#1256000
b11111110 %
b1111100 "
#1260000
0#
#1265000
1#
#1266000
b11111111 %
b1111101 "
#1270000
0#
#1275000
1#
#1276000
b100000000 %
b1111110 "
#1280000
0#
#1285000
0*
1)
1#
#1286000
b100000001 %
b1111111 "
#1290000
0#
#1295000
1#
#1296000
b100000010 %
b10000000 "
#1300000
0#
#1305000
1#
#1306000
b100000011 %
b10000001 "
#1310000
0#
#1315000
1#
#1316000
b100000100 %
b10000010 "
#1320000
0#
#1325000
1#
#1326000
b100000101 %
b10000011 "
#1330000
0#
#1335000
1#
#1336000
b100000110 %
b10000100 "
#1340000
0#
#1345000
1#
#1346000
b100000111 %
b10000101 "
#1350000
0#
#1355000
1#
#1356000
b100001000 %
b10000110 "
#1360000
0#
#1365000
1#
#1366000
b100001001 %
b10000111 "
#1370000
0#
#1375000
1#
#1376000
b100001010 %
b10001000 "
#1380000
0#
#1385000
1#
#1386000
b100001011 %
b10001001 "
#1390000
0#
#1395000
1#
#1396000
b100001100 %
b10001010 "
#1400000
0#
#1405000
1#
#1406000
b100001101 %
b10001011 "
#1410000
0#
#1415000
1#
#1416000
b100001110 %
b10001100 "
#1420000
0#
#1425000
1#
#1426000
b100001111 %
b10001101 "
#1430000
0#
#1435000
1#
#1436000
b100010000 %
b10001110 "
#1440000
0#
#1445000
1#
#1446000
b100010001 %
b10001111 "
#1450000
0#
#1455000
1#
#1456000
b100010010 %
b10010000 "
#1460000
0#
#1465000
1#
#1466000
b100010011 %
b10010001 "
#1470000
0#
#1475000
1#
#1476000
b100010100 %
b10010010 "
#1480000
0#
#1485000
1#
#1486000
b100010101 %
b10010011 "
#1490000
0#
#1495000
1#
#1496000
b100010110 %
b10010100 "
#1500000
0#
#1505000
1#
#1506000
b100010111 %
b10010101 "
#1510000
0#
#1515000
1#
#1516000
b100011000 %
b10010110 "
#1520000
0#
#1525000
1#
#1526000
b100011001 %
b10010111 "
#1530000
0#
#1535000
1#
#1536000
b100011010 %
b10011000 "
#1540000
0#
#1545000
1#
#1546000
b100011011 %
b10011001 "
#1550000
0#
#1555000
1#
#1556000
b100011100 %
b10011010 "
#1560000
0#
#1565000
1#
#1566000
b100011101 %
b10011011 "
#1570000
0#
#1575000
1#
#1576000
b100011110 %
b10011100 "
#1580000
0#
#1585000
1#
#1586000
b100011111 %
b10011101 "
#1590000
0#
#1595000
1#
#1596000
b100100000 %
b10011110 "
#1600000
0#
#1605000
1#
#1606000
b100100001 %
b10011111 "
#1610000
0#
#1615000
1#
#1616000
b100100010 %
b10100000 "
#1620000
0#
#1625000
1#
#1626000
b100100011 %
b10100001 "
#1630000
0#
#1635000
1#
#1636000
b100100100 %
b10100010 "
#1640000
0#
#1645000
1#
#1646000
b100100101 %
b10100011 "
#1650000
0#
#1655000
1#
#1656000
b100100110 %
b10100100 "
#1660000
0#
#1665000
1#
#1666000
b100100111 %
b10100101 "
#1670000
0#
#1675000
1#
#1676000
b100101000 %
b10100110 "
#1680000
0#
#1685000
1#
#1686000
b100101001 %
b10100111 "
#1690000
0#
#1695000
1#
#1696000
b100101010 %
b10101000 "
#1700000
0#
#1705000
1#
#1706000
b100101011 %
b10101001 "
#1710000
0#
#1715000
1#
#1716000
b100101100 %
b10101010 "
#1720000
0#
#1725000
1#
#1726000
b100101101 %
b10101011 "
#1730000
0#
#1735000
1#
#1736000
b100101110 %
b10101100 "
#1740000
0#
#1745000
1#
#1746000
b100101111 %
b10101101 "
#1750000
0#
#1755000
1#
#1756000
b100110000 %
b10101110 "
#1760000
0#
#1765000
1#
#1766000
b100110001 %
b10101111 "
#1770000
0#
#1775000
1#
#1776000
b100110010 %
b10110000 "
#1780000
0#
#1785000
1#
#1786000
b100110011 %
b10110001 "
#1790000
0#
#1795000
1#
#1796000
b100110100 %
b10110010 "
#1800000
0#
#1805000
1#
#1806000
b100110101 %
b10110011 "
#1810000
0#
#1815000
1#
#1816000
b100110110 %
b10110100 "
#1820000
0#
#1825000
1#
#1826000
b100110111 %
b10110101 "
#1830000
0#
#1835000
1#
#1836000
b100111000 %
b10110110 "
#1840000
0#
#1845000
1#
#1846000
b100111001 %
b10110111 "
#1850000
0#
#1855000
1#
#1856000
b100111010 %
b10111000 "
#1860000
0#
#1865000
1#
#1866000
b100111011 %
b10111001 "
#1870000
0#
#1875000
1#
#1876000
b100111100 %
b10111010 "
#1880000
0#
#1885000
1#
#1886000
b100111101 %
b10111011 "
#1890000
0#
#1895000
1#
#1896000
b100111110 %
b10111100 "
#1900000
0#
#1905000
1#
#1906000
b100111111 %
b10111101 "
#1910000
0#
#1915000
1#
#1916000
b101000000 %
b10111110 "
#1920000
0#
#1925000
1#
#1926000
b101000001 %
b10111111 "
#1930000
0#
#1935000
1#
#1936000
b101000010 %
b11000000 "
#1940000
0#
#1945000
1#
#1946000
b101000011 %
b11000001 "
#1950000
0#
#1955000
1#
#1956000
b101000100 %
b11000010 "
#1960000
0#
#1965000
1#
#1966000
b101000101 %
b11000011 "
#1970000
0#
#1975000
1#
#1976000
b101000110 %
b11000100 "
#1980000
0#
#1985000
1#
#1986000
b101000111 %
b11000101 "
#1990000
0#
#1995000
1#
#1996000
b101001000 %
b11000110 "
#2000000
0#
#2005000
1#
#2006000
b101001001 %
b11000111 "
#2010000
0#
#2015000
1#
#2016000
b101001010 %
b11001000 "
#2020000
0#
#2025000
1#
#2026000
b101001011 %
b11001001 "
#2030000
0#
#2035000
1#
#2036000
b101001100 %
b11001010 "
#2040000
0#
#2045000
1#
#2046000
b101001101 %
b11001011 "
#2050000
0#
#2055000
1#
#2056000
b101001110 %
b11001100 "
#2060000
0#
#2065000
1#
#2066000
b101001111 %
b11001101 "
#2070000
0#
#2075000
1#
#2076000
b101010000 %
b11001110 "
#2080000
0#
#2085000
1#
#2086000
b101010001 %
b11001111 "
#2090000
0#
#2095000
1#
#2096000
b101010010 %
b11010000 "
#2100000
0#
#2105000
1#
#2106000
b101010011 %
b11010001 "
#2110000
0#
#2115000
1#
#2116000
b101010100 %
b11010010 "
#2120000
0#
#2125000
1#
#2126000
b101010101 %
b11010011 "
#2130000
0#
#2135000
1#
#2136000
b101010110 %
b11010100 "
#2140000
0#
#2145000
1#
#2146000
b101010111 %
b11010101 "
#2150000
0#
#2155000
1#
#2156000
b101011000 %
b11010110 "
#2160000
0#
#2165000
1#
#2166000
b101011001 %
b11010111 "
#2170000
0#
#2175000
1#
#2176000
b101011010 %
b11011000 "
#2180000
0#
#2185000
1#
#2186000
b101011011 %
b11011001 "
#2190000
0#
#2195000
1#
#2196000
b101011100 %
b11011010 "
#2200000
0#
#2205000
1#
#2206000
b101011101 %
b11011011 "
#2210000
0#
#2215000
1#
#2216000
b101011110 %
b11011100 "
#2220000
0#
#2225000
1#
#2226000
b101011111 %
b11011101 "
#2230000
0#
#2235000
1#
#2236000
b101100000 %
b11011110 "
#2240000
0#
#2245000
1#
#2246000
b101100001 %
b11011111 "
#2250000
0#
#2255000
1#
#2256000
b101100010 %
b11100000 "
#2260000
0#
#2265000
1#
#2266000
b101100011 %
b11100001 "
#2270000
0#
#2275000
1#
#2276000
b101100100 %
b11100010 "
#2280000
0#
#2285000
1#
#2286000
b101100101 %
b11100011 "
#2290000
0#
#2295000
1#
#2296000
b101100110 %
b11100100 "
#2300000
0#
#2305000
1#
#2306000
b101100111 %
b11100101 "
#2310000
0#
#2315000
1#
#2316000
b101101000 %
b11100110 "
#2320000
0#
#2325000
1#
#2326000
b101101001 %
b11100111 "
#2330000
0#
#2335000
1#
#2336000
b101101010 %
b11101000 "
#2340000
0#
#2345000
1#
#2346000
b101101011 %
b11101001 "
#2350000
0#
#2355000
1#
#2356000
b101101100 %
b11101010 "
#2360000
0#
#2365000
1#
#2366000
b101101101 %
b11101011 "
#2370000
0#
#2375000
1#
#2376000
b101101110 %
b11101100 "
#2380000
0#
#2385000
1#
#2386000
b101101111 %
b11101101 "
#2390000
0#
#2395000
1#
#2396000
b101110000 %
b11101110 "
#2400000
0#
#2405000
1#
#2406000
b101110001 %
b11101111 "
#2410000
0#
#2415000
1#
#2416000
b101110010 %
b11110000 "
#2420000
0#
#2425000
1#
#2426000
b101110011 %
b11110001 "
#2430000
0#
#2435000
1#
#2436000
b101110100 %
b11110010 "
#2440000
0#
#2445000
1#
#2446000
b101110101 %
b11110011 "
#2450000
0#
#2455000
1#
#2456000
b101110110 %
b11110100 "
#2460000
0#
#2465000
1#
#2466000
b101110111 %
b11110101 "
#2470000
0#
#2475000
1#
#2476000
b101111000 %
b11110110 "
#2480000
0#
#2485000
1#
#2486000
b101111001 %
b11110111 "
#2490000
0#
#2495000
1#
#2496000
b101111010 %
b11111000 "
#2500000
0#
#2505000
1#
#2506000
b101111011 %
b11111001 "
#2510000
0#
#2515000
1#
#2516000
b101111100 %
b11111010 "
#2520000
0#
#2525000
1#
#2526000
b101111101 %
b11111011 "
#2530000
0#
#2535000
1#
#2536000
b101111110 %
b11111100 "
#2540000
0#
#2545000
1#
#2546000
b101111111 %
b11111101 "
#2550000
0#
#2555000
1#
#2556000
b110000000 %
b11111110 "
#2560000
0#
#2565000
1#
#2566000
b110000001 %
b11111111 "
#2570000
0#
#2575000
1#
#2576000
b1 "
b10000100 %
b10 !
#2580000
0#
#2585000
1*
0)
1#
#2586000
b10000101 %
b10 "
#2590000
0#
#2595000
1#
#2596000
b10000110 %
b11 "
#2600000
0#
#2605000
1#
#2606000
b10000111 %
b100 "
#2610000
0#
#2615000
1#
#2616000
b10001000 %
b101 "
#2620000
0#
#2625000
1#
#2626000
b10001001 %
b110 "
#2630000
0#
#2635000
1#
#2636000
b10001010 %
b111 "
#2640000
0#
#2645000
1#
#2646000
b10001011 %
b1000 "
#2650000
0#
#2655000
1#
#2656000
b10001100 %
b1001 "
#2660000
0#
#2665000
1#
#2666000
b10001101 %
b1010 "
#2670000
0#
#2675000
1#
#2676000
b10001110 %
b1011 "
#2680000
0#
#2685000
1#
#2686000
b10001111 %
b1100 "
#2690000
0#
#2695000
1#
#2696000
b10010000 %
b1101 "
#2700000
0#
#2705000
1#
#2706000
b10010001 %
b1110 "
#2710000
0#
#2715000
1#
#2716000
b10010010 %
b1111 "
#2720000
0#
#2725000
1#
#2726000
b10010011 %
b10000 "
#2730000
0#
#2735000
1#
#2736000
b10010100 %
b10001 "
#2740000
0#
#2745000
1#
#2746000
b10010101 %
b10010 "
#2750000
0#
#2755000
1#
#2756000
b10010110 %
b10011 "
#2760000
0#
#2765000
1#
#2766000
b10010111 %
b10100 "
#2770000
0#
#2775000
1#
#2776000
b10011000 %
b10101 "
#2780000
0#
#2785000
1#
#2786000
b10011001 %
b10110 "
#2790000
0#
#2795000
1#
#2796000
b10011010 %
b10111 "
#2800000
0#
#2805000
1#
#2806000
b10011011 %
b11000 "
#2810000
0#
#2815000
1#
#2816000
b10011100 %
b11001 "
#2820000
0#
#2825000
1#
#2826000
b10011101 %
b11010 "
#2830000
0#
#2835000
1#
#2836000
b10011110 %
b11011 "
#2840000
0#
#2845000
1#
#2846000
b10011111 %
b11100 "
#2850000
0#
#2855000
1#
#2856000
b10100000 %
b11101 "
#2860000
0#
#2865000
1#
#2866000
b10100001 %
b11110 "
#2870000
0#
#2875000
1#
#2876000
b10100010 %
b11111 "
#2880000
0#
#2885000
1#
#2886000
b10100011 %
b100000 "
#2890000
0#
#2895000
1#
#2896000
b10100100 %
b100001 "
#2900000
0#
#2905000
1#
#2906000
b10100101 %
b100010 "
#2910000
0#
#2915000
1#
#2916000
b10100110 %
b100011 "
#2920000
0#
#2925000
1#
#2926000
b10100111 %
b100100 "
#2930000
0#
#2935000
1#
#2936000
b10101000 %
b100101 "
#2940000
0#
#2945000
1#
#2946000
b10101001 %
b100110 "
#2950000
0#
#2955000
1#
#2956000
b10101010 %
b100111 "
#2960000
0#
#2965000
1#
#2966000
b10101011 %
b101000 "
#2970000
0#
#2975000
1#
#2976000
b10101100 %
b101001 "
#2980000
0#
#2985000
1#
#2986000
b10101101 %
b101010 "
#2990000
0#
#2995000
1#
#2996000
b10101110 %
b101011 "
#3000000
0#
#3005000
1#
#3006000
b10101111 %
b101100 "
#3010000
0#
#3015000
1#
#3016000
b10110000 %
b101101 "
#3020000
0#
#3025000
1#
#3026000
b10110001 %
b101110 "
#3030000
0#
#3035000
1#
#3036000
b10110010 %
b101111 "
#3040000
0#
#3045000
1#
#3046000
b10110011 %
b110000 "
#3050000
0#
#3055000
1#
#3056000
b10110100 %
b110001 "
#3060000
0#
#3065000
1#
#3066000
b10110101 %
b110010 "
#3070000
0#
#3075000
1#
#3076000
b10110110 %
b110011 "
#3080000
0#
#3085000
1#
#3086000
b10110111 %
b110100 "
#3090000
0#
#3095000
1#
#3096000
b10111000 %
b110101 "
#3100000
0#
#3105000
1#
#3106000
b10111001 %
b110110 "
#3110000
0#
#3115000
1#
#3116000
b10111010 %
b110111 "
#3120000
0#
#3125000
1#
#3126000
b10111011 %
b111000 "
#3130000
0#
#3135000
1#
#3136000
b10111100 %
b111001 "
#3140000
0#
#3145000
1#
#3146000
b10111101 %
b111010 "
#3150000
0#
#3155000
1#
#3156000
b10111110 %
b111011 "
#3160000
0#
#3165000
1#
#3166000
b10111111 %
b111100 "
#3170000
0#
#3175000
1#
#3176000
b11000000 %
b111101 "
#3180000
0#
#3185000
1#
#3186000
b11000001 %
b111110 "
#3190000
0#
#3195000
1#
#3196000
b11000010 %
b111111 "
#3200000
0#
#3205000
1#
#3206000
b11000011 %
b1000000 "
#3210000
0#
#3215000
1#
#3216000
b11000100 %
b1000001 "
#3220000
0#
#3225000
1#
#3226000
b11000101 %
b1000010 "
#3230000
0#
#3235000
1#
#3236000
b11000110 %
b1000011 "
#3240000
0#
#3245000
1#
#3246000
b11000111 %
b1000100 "
#3250000
0#
#3255000
1#
#3256000
b11001000 %
b1000101 "
#3260000
0#
#3265000
1#
#3266000
b11001001 %
b1000110 "
#3270000
0#
#3275000
1#
#3276000
b11001010 %
b1000111 "
#3280000
0#
#3285000
1#
#3286000
b11001011 %
b1001000 "
#3290000
0#
#3295000
1#
#3296000
b11001100 %
b1001001 "
#3300000
0#
#3305000
1#
#3306000
b11001101 %
b1001010 "
#3310000
0#
#3315000
1#
#3316000
b11001110 %
b1001011 "
#3320000
0#
#3325000
1#
#3326000
b11001111 %
b1001100 "
#3330000
0#
#3335000
1#
#3336000
b11010000 %
b1001101 "
#3340000
0#
#3345000
1#
#3346000
b11010001 %
b1001110 "
#3350000
0#
#3355000
1#
#3356000
b11010010 %
b1001111 "
#3360000
0#
#3365000
1#
#3366000
b11010011 %
b1010000 "
#3370000
0#
#3375000
1#
#3376000
b11010100 %
b1010001 "
#3380000
0#
#3385000
1#
#3386000
b11010101 %
b1010010 "
#3390000
0#
#3395000
1#
#3396000
b11010110 %
b1010011 "
#3400000
0#
#3405000
1#
#3406000
b11010111 %
b1010100 "
#3410000
0#
#3415000
1#
#3416000
b11011000 %
b1010101 "
#3420000
0#
#3425000
1#
#3426000
b11011001 %
b1010110 "
#3430000
0#
#3435000
1#
#3436000
b11011010 %
b1010111 "
#3440000
0#
#3445000
1#
#3446000
b11011011 %
b1011000 "
#3450000
0#
#3455000
1#
#3456000
b11011100 %
b1011001 "
#3460000
0#
#3465000
1#
#3466000
b11011101 %
b1011010 "
#3470000
0#
#3475000
1#
#3476000
b11011110 %
b1011011 "
#3480000
0#
#3485000
1#
#3486000
b11011111 %
b1011100 "
#3490000
0#
#3495000
1#
#3496000
b11100000 %
b1011101 "
#3500000
0#
#3505000
1#
#3506000
b11100001 %
b1011110 "
